AUTHORS.rst
CONTRIBUTING.rst
HISTORY.rst
LICENSE
MANIFEST.in
README.rst
setup.cfg
setup.py
cmsplugin_plain_text/__init__.py
cmsplugin_plain_text/cms_plugins.py
cmsplugin_plain_text/models.py
cmsplugin_plain_text.egg-info/PKG-INFO
cmsplugin_plain_text.egg-info/SOURCES.txt
cmsplugin_plain_text.egg-info/dependency_links.txt
cmsplugin_plain_text.egg-info/not-zip-safe
cmsplugin_plain_text.egg-info/top_level.txt
cmsplugin_plain_text/migrations/0001_initial.py
cmsplugin_plain_text/migrations/__init__.py
cmsplugin_plain_text/south_migrations/0001_initial.py
cmsplugin_plain_text/south_migrations/__init__.py
cmsplugin_plain_text/templates/cms/plugins/plaintext.html