Metadata-Version: 1.1
Name: cmsplugin-plain-text
Version: 0.1.0
Summary: A simple plaintext plugin for django CMS.
Home-page: https://github.com/chschuermann/cmsplugin-plain-text
Author: Christian Schürmann
Author-email: christian.schuermann@bluewin.ch
License: BSD
Keywords: cmsplugin-plain-text
Platform: UNKNOWN
Classifier: Development Status :: 3 - Alpha
Classifier: Framework :: Django
Classifier: Framework :: Django :: 1.7
Classifier: Framework :: Django :: 1.8
Classifier: Intended Audience :: Developers
Classifier: License :: OSI Approved :: BSD License
Classifier: Natural Language :: English
Classifier: Programming Language :: Python :: 2
Classifier: Programming Language :: Python :: 2.7
Classifier: Programming Language :: Python :: 3
Classifier: Programming Language :: Python :: 3.3
Classifier: Programming Language :: Python :: 3.4
Classifier: Programming Language :: Python :: 3.5
